Workbook

Sheet Lisez-moi
B2: Analyse des recettes Senelec — alternative à la tarification Woyofal
B4: Classeur compagnon du document « Tarification Woyofal : une alternative » (docs/tarification_alternative_woyofal.pdf).
B5: Il chiffre l'incidence sur les recettes de Senelec des quatre composantes : (A) fenêtre glissante et redevance au
B6: prorata, (B) multiplicateur de partage, (C) tarif social ciblé, (D) bi-horaire.
B8: LÉGENDE — cellules à modifier :
B9: • Texte BLEU = hypothèse modifiable ; fond JAUNE = hypothèse clé (illustrative, à caler sur les données Senelec).
B10: • Texte NOIR = formule (ne pas écraser) ; texte VERT = lien vers une autre feuille.
B12: SOURCES :
B13: • Grille tarifaire : CRSE, décision n°2025-140 du 26/12/2025 (en vigueur au 01/01/2026), catégorie DPP.
B14: • Coût de production ~117 F/kWh : déclaration gouvernementale, avril 2025 (Africa Check).
B15: • Compensation tarifaire due ~193 Mds F à fin nov. 2025 : Le Soleil / CRSE.
B16: • Coût complet κ = 140 F/kWh, α, β, parc : hypothèses ILLUSTRATIVES fournies par l'utilisateur / à caler.
... B20: consommation par compteur de Senelec (distribution des volumes par tranche).

Sheet Paramètres
A1: Paramètres du modèle
A3: Grille CRSE 2026 (décision n°2025-140, DPP)
A4: p1 — prix Tranche 1 | B4: 82 | C4: F/kWh
A5: p2 — prix Tranche 2 | B5: 136.49 | C5: F/kWh
A6: p3 — prix Tranche 3 (post-paid) | B6: 159.36 | C6: F/kWh
A7: L — limite Tranche 1 | B7: 150 | C7: kWh/mois
A8: S — seuil TVA | B8: 250 | C8: kWh/mois
A9: Taxe communale (τc) | B9: 0.025
A10: TVA (τv) | B10: 0.18
A11: R — redevance monophasé | B11: 429 | C11: F/mois
A12: R — redevance triphasé | B12: 1427 | C12: F/mois
A14: Coûts de fourniture
A15: κ_prod — coût de production | B15: 117 | C15: F/kWh | D15: Déclaration gouvernementale avril 2025
A16: κ — coût complet de fourniture | B16: 140 | C16: F/kWh | D16: ILLUSTRATIF : production + réseau + commercialisation
A17: κ_hp — coût marginal en pointe (fioul) | B17: 160 | C17: F/kWh | D17: ILLUSTRATIF
A18: κ_hc — coût marginal hors pointe (gaz/solaire) | B18: 90 | C18: F/kWh | D18: ILLUSTRATIF
A20: Parc et comportements (hypothèses)
A21: Parc de compteurs Woyofal | B21: 2000000 | C21: compteurs | D21: Ordre de grandeur public (>2 M)
A22: Part des compteurs dépassant L chaque mois | B22: 0.35 | D22: ILLUSTRATIF
A23: α — part des volumes T1 allant aux éligibles | B23: 0.5 | D23: ILLUSTRATIF — pilote le tarif social atteignable
A24: β — part de la consommation en pointe (19h-23h) | B24: 0.35 | D24: ILLUSTRATIF
A25: p̄ — prix uniforme hors bloc social (D) | B25: 110 | C25: F/kWh | D25: ILLUSTRATIF
A26: σ* — écart bi-horaire coût-reflet (= κ_hp − κ_hc) | B26: =B17-B18 -> 70 | C26: F/kWh
A27: Taux de saturation de la Tranche 1 | B27: 0.7 | D27: Part des capacités T1 (150 kWh × parc) réellement vendues
A28: Compteurs partagés déclarés (composante B) | B28: 100000 | C28: compteurs | D28: Hypothèse d'adoption
A29: H moyen des compteurs déclarés | B29: 3 | C29: ménages
A30: Plafond du rattrapage de redevance | B30: 2 | C30: mois
A31: Volume T1 annuel V1 (= parc × L × 12 × saturation) | B31: =B21*B7*12*B27 -> 2520000000 | C31: kWh/an

Sheet A_Arbitrage
A1: (A) Fenêtre glissante — fuite d'arbitrage calendaire refermée
A3: Borne de gain d'arbitrage par ménage et par mois (Prop. 4) : | B3: =Paramètres!B7*(Paramètres!B5-Paramètres!B4)*(1+Paramètres!B9) -> 8377.8375
A4: Hypothèse : les « optimisateurs » sont des compteurs dépassant L qui exploitent la frontière au plafond.
A6: Exposition annuelle selon la part de compteurs optimisateurs
A7: Part du parc optimisatrice | B7: Compteurs concernés | C7: Exposition annuelle (Mds F)
A8: 0 | B8: =A8*Paramètres!B21 -> 0 | C8: =B8*$B$3*12/1000000000 -> 0
A9: 0.01 | B9: =A9*Paramètres!B21 -> 20000 | C9: =B9*$B$3*12/1000000000 -> 2.010681
A10: 0.02 | B10: =A10*Paramètres!B21 -> 40000 | C10: =B10*$B$3*12/1000000000 -> 4.021362
A11: 0.03 | B11: =A11*Paramètres!B21 -> 60000 | C11: =B11*$B$3*12/1000000000 -> 6.032043
A12: 0.04 | B12: =A12*Paramètres!B21 -> 80000 | C12: =B12*$B$3*12/1000000000 -> 8.042724
A13: 0.05 | B13: =A13*Paramètres!B21 -> 100000 | C13: =B13*$B$3*12/1000000000 -> 10.053405
A14: 0.06 | B14: =A14*Paramètres!B21 -> 120000 | C14: =B14*$B$3*12/1000000000 -> 12.064086
A15: 0.07 | B15: =A15*Paramètres!B21 -> 140000 | C15: =B15*$B$3*12/1000000000 -> 14.074767
A16: 0.08 | B16: =A16*Paramètres!B21 -> 160000 | C16: =B16*$B$3*12/1000000000 -> 16.085448
A17: 0.09 | B17: =A17*Paramètres!B21 -> 180000 | C17: =B17*$B$3*12/1000000000 -> 18.096129
A18: 0.1 | B18: =A18*Paramètres!B21 -> 200000 | C18: =B18*$B$3*12/1000000000 -> 20.10681
A20: Lecture : cette recette n'est PAS perdue aujourd'hui (usagers peu informés) — c'est l'exposition vers laquelle
A21: le statu quo dérive à mesure que les usagers apprennent l'arbitrage. La fenêtre glissante la ramène à zéro.

Sheet A_Redevance
A1: (A) Redevance au prorata — montants prélevés selon le scénario
A3: Scénario (monophasé) | B3: Régime actuel (calendaire) | C3: Prorata R·δ/T (plafonné)
A4: Client régulier — recharges tous les 30 jours | B4: =Paramètres!B11 -> 429 | C4: =Paramètres!B11*30/30 -> 429
A5: Frontière de mois — 2e recharge 2 jours après (31 janv. → 2 fév.) | B5: =Paramètres!B11 -> 429 | C5: =Paramètres!B11*2/30 -> 28.6
A6: Retour après 3 mois sans recharge (rattrapage) | B6: =3*Paramètres!B11 -> 1287 | C6: =Paramètres!B11*MIN(3,Paramètres!B30) -> 858
A8: Le prélèvement « frontière » actuel (429 F pour 2 jours de location) figure parmi les anomalies relevées
A9: par l'enquête CRSE (doubles prélèvements). Le plafond du rattrapage est un curseur commercial (Paramètres!B30).

Sheet C_Ciblage
A1: (C) Tarif social ciblé — neutralité budgétaire (Thm 3)
A3: p_s neutre = κ − (κ − p1)/α en fonction de α
A4: α | B4: p_s neutre (F/kWh) | C4: Facture éligible 100 kWh (F/mois)
A5: 0.42 | B5: =MAX(0,Paramètres!$B$16-(Paramètres!$B$16-Paramètres!$B$4)/A5) -> 1.9047619 | C5: =100*B5*(1+Paramètres!$B$9)+Paramètres!$B$11 -> 624.2381
A6: 0.45 | B6: =MAX(0,Paramètres!$B$16-(Paramètres!$B$16-Paramètres!$B$4)/A6) -> 11.111111 | C6: =100*B6*(1+Paramètres!$B$9)+Paramètres!$B$11 -> 1567.8889
A7: 0.5 | B7: =MAX(0,Paramètres!$B$16-(Paramètres!$B$16-Paramètres!$B$4)/A7) -> 24 | C7: =100*B7*(1+Paramètres!$B$9)+Paramètres!$B$11 -> 2889
A8: 0.55 | B8: =MAX(0,Paramètres!$B$16-(Paramètres!$B$16-Paramètres!$B$4)/A8) -> 34.545455 | C8: =100*B8*(1+Paramètres!$B$9)+Paramètres!$B$11 -> 3969.9091
A9: 0.6 | B9: =MAX(0,Paramètres!$B$16-(Paramètres!$B$16-Paramètres!$B$4)/A9) -> 43.333333 | C9: =100*B9*(1+Paramètres!$B$9)+Paramètres!$B$11 -> 4870.6667
A10: 0.65 | B10: =MAX(0,Paramètres!$B$16-(Paramètres!$B$16-Paramètres!$B$4)/A10) -> 50.769231 | C10: =100*B10*(1+Paramètres!$B$9)+Paramètres!$B$11 -> 5632.8462
A11: 0.7 | B11: =MAX(0,Paramètres!$B$16-(Paramètres!$B$16-Paramètres!$B$4)/A11) -> 57.142857 | C11: =100*B11*(1+Paramètres!$B$9)+Paramètres!$B$11 -> 6286.1429
A12: 0.75 | B12: =MAX(0,Paramètres!$B$16-(Paramètres!$B$16-Paramètres!$B$4)/A12) -> 62.666667 | C12: =100*B12*(1+Paramètres!$B$9)+Paramètres!$B$11 -> 6852.3333
A13: 0.8 | B13: =MAX(0,Paramètres!$B$16-(Paramètres!$B$16-Paramètres!$B$4)/A13) -> 67.5 | C13: =100*B13*(1+Paramètres!$B$9)+Paramètres!$B$11 -> 7347.75
A14: 0.85 | B14: =MAX(0,Paramètres!$B$16-(Paramètres!$B$16-Paramètres!$B$4)/A14) -> 71.764706 | C14: =100*B14*(1+Paramètres!$B$9)+Paramètres!$B$11 -> 7784.8824
A15: 0.9 | B15: =MAX(0,Paramètres!$B$16-(Paramètres!$B$16-Paramètres!$B$4)/A15) -> 75.555556 | C15: =100*B15*(1+Paramètres!$B$9)+Paramètres!$B$11 -> 8173.4444
A16: 0.95 | B16: =MAX(0,Paramètres!$B$16-(Paramètres!$B$16-Paramètres!$B$4)/A16) -> 78.947368 | C16: =100*B16*(1+Paramètres!$B$9)+Paramètres!$B$11 -> 8521.1053
A17: 1 | B17: =MAX(0,Paramètres!$B$16-(Paramètres!$B$16-Paramètres!$B$4)/A17) -> 82 | C17: =100*B17*(1+Paramètres!$B$9)+Paramètres!$B$11 -> 8834
A20: Décomposition annuelle : guichet vs compensation d'État
A21: p_s choisi (par défaut : le p_s neutre à l'α des Paramètres) : | B21: =MAX(0,Paramètres!B16-(Paramètres!B16-Paramètres!B4)/Paramètres!B23) -> 24
A23: Poste (volumes Tranche 1, Mds F/an) | B23: Avant (grille actuelle) | C23: Après (ciblage)
A24: Recette guichet (payée par les clients) | B24: =Paramètres!B4*Paramètres!B31/1000000000 -> 206.64 | C24: =(Paramètres!B16*(1-Paramètres!B23)+B21*Paramètres!B23)*Paramètres!B31/1000000000 -> 206.64
A25: Compensation d'État (subvention du bloc) | B25: =(Paramètres!B16-Paramètres!B4)*Paramètres!B31/1000000000 -> 146.16 | C25: =(Paramètres!B16-B21)*Paramètres!B23*Paramètres!B31/1000000000 -> 146.16
A26: Total (= κ × V1, invariant) | B26: =B24+B25 -> 352.8 | C26: =C24+C25 -> 352.8
A28: Au p_s neutre, guichet et compensation sont inchangés au total : seule l'incidence change (qui est subventionné).
A29: Monter p_s au-dessus du neutre réduit la compensation (économie d'État) au prix d'une remise moins profonde.

Sheet D_BiHoraire
A1: (D) Bi-horaire — calibrage neutre en recette et gain de bascule
A3: Prix heures creuses p_hc = p̄ − β·σ* | B3: =Paramètres!B25-Paramètres!B24*Paramètres!B26 -> 85.5
A4: Prix heures pleines p_hp = p̄ + (1−β)·σ* | B4: =Paramètres!B25+(1-Paramètres!B24)*Paramètres!B26 -> 155.5
A5: Vérification neutralité : β·p_hp + (1−β)·p_hc | B5: =Paramètres!B24*B4+(1-Paramètres!B24)*B3 -> 110
A6: La vérification doit redonner p̄ (Paramètres!B25) : recette et facture moyenne inchangées.
A8: Gain d'une bascule de consommation hors pointe (par ménage)
A9: kWh basculés / mois | B9: Économie ménage (σ*·Δq) | C9: Économie système ((κhp−κhc)·Δq)
A10: 0 | B10: =A10*Paramètres!$B$26 -> 0 | C10: =A10*(Paramètres!$B$17-Paramètres!$B$18) -> 0
A11: 5 | B11: =A11*Paramètres!$B$26 -> 350 | C11: =A11*(Paramètres!$B$17-Paramètres!$B$18) -> 350
A12: 10 | B12: =A12*Paramètres!$B$26 -> 700 | C12: =A12*(Paramètres!$B$17-Paramètres!$B$18) -> 700
A13: 15 | B13: =A13*Paramètres!$B$26 -> 1050 | C13: =A13*(Paramètres!$B$17-Paramètres!$B$18) -> 1050
A14: 20 | B14: =A14*Paramètres!$B$26 -> 1400 | C14: =A14*(Paramètres!$B$17-Paramètres!$B$18) -> 1400
A15: 25 | B15: =A15*Paramètres!$B$26 -> 1750 | C15: =A15*(Paramètres!$B$17-Paramètres!$B$18) -> 1750
A16: 30 | B16: =A16*Paramètres!$B$26 -> 2100 | C16: =A16*(Paramètres!$B$17-Paramètres!$B$18) -> 2100
A17: 35 | B17: =A17*Paramètres!$B$26 -> 2450 | C17: =A17*(Paramètres!$B$17-Paramètres!$B$18) -> 2450
A18: 40 | B18: =A18*Paramètres!$B$26 -> 2800 | C18: =A18*(Paramètres!$B$17-Paramètres!$B$18) -> 2800
A19: 45 | B19: =A19*Paramètres!$B$26 -> 3150 | C19: =A19*(Paramètres!$B$17-Paramètres!$B$18) -> 3150
A20: 50 | B20: =A20*Paramètres!$B$26 -> 3500 | C20: =A20*(Paramètres!$B$17-Paramètres!$B$18) -> 3500
A22: Au calibrage coût-reflet (σ* = κhp − κhc), les deux colonnes coïncident : le signal est auto-financé (Prop. 9c).

Sheet Synthèse
A1: Synthèse — incidence annuelle sur les recettes Senelec
A3: Composante | B3: Mécanisme | C3: Montant annuel (Mds F) | D3: Nature
A4: (A) Fenêtre glissante | B4: Fuite d'arbitrage calendaire refermée (exposition à 5 % d'optimisateurs) | C4: =A_Arbitrage!C13 -> 10.053405 | D4: Gain évité (structurel)
A5: (B) Multiplicateur de partage | B5: Borne : 8 378 × (H−1) × compteurs déclarés × 12 | C5: =-A_Arbitrage!B3*(Paramètres!B29-1)*Paramètres!B28*12/1000000000 -> -20.10681 | D5: Coût d'équité, borné, absorbable dans α
A6: (C) Tarif social ciblé (p_s neutre) | B6: Écart de compensation vs aujourd'hui (0 par construction au p_s neutre) | C6: =C_Ciblage!B25-C_Ciblage!C25 -> 0 | D6: Neutre (théorème) ; curseur p_s
A7: (D) Bi-horaire | B7: Fioul de pointe évité : 10 kWh basculés/mois × 30 % du parc | C7: =10*(Paramètres!B17-Paramètres!B18)*0.3*Paramètres!B21*12/1000000000 -> 5.04 | D7: Baisse de coûts, recette inchangée
A9: Convention de signe : positif = recette préservée/coût évité ; négatif = manque à gagner assumé.
A10: Le paquet est conçu pour être au pire neutre : le seul poste négatif (B) est borné et se finance dans le
A11: recalibrage de (C) (les ménages déclarés entrent dans α).
